odoo10_addon_base_phone-10.0.0.1.0-py2.7-nspkg.pth
odoo10_addon_base_phone-10.0.0.1.0.dist-info/top_level.txt
odoo10_addon_base_phone-10.0.0.1.0.dist-info/WHEEL
odoo10_addon_base_phone-10.0.0.1.0.dist-info/RECORD
odoo10_addon_base_phone-10.0.0.1.0.dist-info/metadata.json
odoo10_addon_base_phone-10.0.0.1.0.dist-info/DESCRIPTION.rst
odoo10_addon_base_phone-10.0.0.1.0.dist-info/METADATA
odoo10_addon_base_phone-10.0.0.1.0.dist-info/namespace_packages.txt
odoo/addons/base_phone/__manifest__.py
odoo/addons/base_phone/fields.py
odoo/addons/base_phone/web_phone.xml
odoo/addons/base_phone/__init__.py
odoo/addons/base_phone/requirements.txt
odoo/addons/base_phone/README.rst
odoo/addons/base_phone/security/phone_security.xml
odoo/addons/base_phone/security/ir.model.access.csv
odoo/addons/base_phone/models/res_partner.py
odoo/addons/base_phone/models/__init__.py
odoo/addons/base_phone/models/res_company.py
odoo/addons/base_phone/models/phone_common.py
odoo/addons/base_phone/i18n/ru.po
odoo/addons/base_phone/i18n/pt.po
odoo/addons/base_phone/i18n/it.po
odoo/addons/base_phone/i18n/es.po
odoo/addons/base_phone/i18n/nl_BE.po
odoo/addons/base_phone/i18n/ar.po
odoo/addons/base_phone/i18n/lt.po
odoo/addons/base_phone/i18n/ro.po
odoo/addons/base_phone/i18n/tr.po
odoo/addons/base_phone/i18n/es_EC.po
odoo/addons/base_phone/i18n/gl.po
odoo/addons/base_phone/i18n/ca.po
odoo/addons/base_phone/i18n/es_CR.po
odoo/addons/base_phone/i18n/sl.po
odoo/addons/base_phone/i18n/base_phone.pot
odoo/addons/base_phone/i18n/th.po
odoo/addons/base_phone/i18n/es_ES.po
odoo/addons/base_phone/i18n/cs.po
odoo/addons/base_phone/i18n/pt_PT.po
odoo/addons/base_phone/i18n/et.po
odoo/addons/base_phone/i18n/nl.po
odoo/addons/base_phone/i18n/am.po
odoo/addons/base_phone/i18n/de.po
odoo/addons/base_phone/i18n/vi.po
odoo/addons/base_phone/i18n/fr.po
odoo/addons/base_phone/i18n/pl.po
odoo/addons/base_phone/i18n/pt_BR.po
odoo/addons/base_phone/i18n/el_GR.po
odoo/addons/base_phone/i18n/es_VE.po
odoo/addons/base_phone/i18n/es_MX.po
odoo/addons/base_phone/i18n/fi.po
odoo/addons/base_phone/wizard/number_not_found.py
odoo/addons/base_phone/wizard/reformat_all_phonenumbers.py
odoo/addons/base_phone/wizard/number_not_found_view.xml
odoo/addons/base_phone/wizard/reformat_all_phonenumbers_view.xml
odoo/addons/base_phone/wizard/__init__.py
