Metadata-Version: 2.0
Name: odoo10-addon-base-phone
Version: 10.0.0.1.0
Summary: Validate phone numbers
Home-page: http://www.akretion.com/
Author: UNKNOWN
Author-email: UNKNOWN
License: AGPL-3
Platform: UNKNOWN
Requires-Dist: odoo (<10.1dev,>=10.0)
Requires-Dist: phonenumbers
Classifier: Programming Language :: Python :: 2.7
Classifier: Framework :: Odoo
Classifier: License :: OSI Approved :: GNU Affero General Public License v3
